identificador_pii/__init__.py
identificador_pii/files/nomes_e_sobrenomes_comuns.txt
identificador_pii/identificador.py
identificador_pii/patterns.json
identificador_pii/teste.ipynb
identificador_pii/utils.py
identificador_pii-0.1.6.dist-info/METADATA
identificador_pii-0.1.6.dist-info/WHEEL
identificador_pii-0.1.6.dist-info/RECORD
