Metadata-Version: 2.1
Name: identificador-pii
Version: 0.1.6
Summary: Este pacote visa criar uma ferramenta simples que pode auxiliar pessoas que trbalham com dados a identificar se em um determinado conjunto de dados, existem dados pessoais.
License: MIT
Author: Pedro Campagna
Author-email: pedrohcmds@gmail.com
Requires-Python: >=3.9,<4.0
Classifier: Development Status :: 4 - Beta
Classifier: License :: OSI Approved :: MIT License
Classifier: Natural Language :: Portuguese (Brazilian)
Classifier: Programming Language :: Python :: 3
Classifier: Programming Language :: Python :: 3.9
Classifier: Programming Language :: Python :: 3.10
Classifier: Programming Language :: Python :: 3.11
Classifier: Programming Language :: Python :: 3.12
Classifier: Topic :: Education
Requires-Dist: pandas (>=2.2.2,<3.0.0)
